cleannaming.py
cleannaming/__init__.py
cleannaming/cleannaming.py
cleannaming-0.0.4.dist-info/DESCRIPTION.rst
cleannaming-0.0.4.dist-info/METADATA
cleannaming-0.0.4.dist-info/RECORD
cleannaming-0.0.4.dist-info/WHEEL
cleannaming-0.0.4.dist-info/entry_points.txt
cleannaming-0.0.4.dist-info/metadata.json
cleannaming-0.0.4.dist-info/top_level.txt
