Metadata-Version: 2.0
Name: cleannaming
Version: 0.0.4
Summary: Clean your naming.
Home-page: https://github.com/DmytryiStriletskyi/cleannaming
Author: DmytryiStriletskyi
Author-email: dmytryi.striletskyi@gmail.com
License: UNKNOWN
Download-URL: https://github.com/DmytryiStriletskyi/cleannaming.zip
Platform: UNKNOWN
Classifier: Programming Language :: Python :: 3.5
